.gitignore
LICENSE.txt
README.md
setup.cfg
setup.py
deplib/__init__.py
deplib.egg-info/PKG-INFO
deplib.egg-info/SOURCES.txt
deplib.egg-info/dependency_links.txt
deplib.egg-info/top_level.txt