Metadata-Version: 1.1
Name: deplib
Version: 1.0.10
Summary: An elegant way to provide an app specific lib dir at runtime.
Home-page: https://github.com/timpeoples/deplib
Author: Tim Peoples
Author-email: pydev@toolman.org
License: GPL
Download-URL: https://github.com/timpeoples/deplib/releases
Keywords: deployment,path,isolation,dependencies
Platform: UNKNOWN
